MANIFEST.in
portal_claim_view.xml
setup.py
./__init__.py
./__openerp__.py
i18n/ar.po
i18n/cs.po
i18n/de.po
i18n/en_GB.po
i18n/es.po
i18n/fi.po
i18n/fr.po
i18n/hr.po
i18n/hu.po
i18n/it.po
i18n/mk.po
i18n/nl.po
i18n/pl.po
i18n/portal_claim.pot
i18n/pt.po
i18n/pt_BR.po
i18n/ro.po
i18n/sl.po
i18n/tr.po
i18n/zh_CN.po
openerp_portal_claim.egg-info/PKG-INFO
openerp_portal_claim.egg-info/SOURCES.txt
openerp_portal_claim.egg-info/dependency_links.txt
openerp_portal_claim.egg-info/requires.txt
openerp_portal_claim.egg-info/top_level.txt
security/ir.model.access.csv
security/portal_security.xml